modapsclient/__init__.py
modapsclient/modapsclient.py
modapsclient-0.1.1.dist-info/DESCRIPTION.rst
modapsclient-0.1.1.dist-info/LICENSE.txt
modapsclient-0.1.1.dist-info/METADATA
modapsclient-0.1.1.dist-info/RECORD
modapsclient-0.1.1.dist-info/WHEEL
modapsclient-0.1.1.dist-info/metadata.json
modapsclient-0.1.1.dist-info/top_level.txt
